bioshed.py
bioshed/__init__.py
bioshed/bioshed.py
bioshed/bioshed_core_utils.py
bioshed/bioshed_deploy_core.py
bioshed/bioshed_init.py
bioshed/src/__init__.py
bioshed/src/bioshed.py
bioshed/src/bioshed_core_utils.py
bioshed/src/bioshed_deploy_core.py
bioshed/src/bioshed_init.py
bioshed/src/bioshed_atlas/__init__.py
bioshed/src/bioshed_atlas/atlas_encode_utils.py
bioshed/src/bioshed_atlas/atlas_tcga_utils.py
bioshed/src/bioshed_atlas/atlas_utils.py
bioshed/src/bioshed_atlas/bioshed_utils/__init__.py
bioshed/src/bioshed_atlas/bioshed_utils/aws_batch_utils.py
bioshed/src/bioshed_atlas/bioshed_utils/aws_s3_utils.py
bioshed/src/bioshed_atlas/bioshed_utils/docker_utils.py
bioshed/src/bioshed_atlas/bioshed_utils/file_utils.py
bioshed/src/bioshed_atlas/bioshed_utils/lambda_utils.py
bioshed/src/bioshed_atlas/bioshed_utils/program_utils.py
bioshed/src/bioshed_atlas/bioshed_utils/quick_utils.py
bioshed/src/bioshed_atlas/bioshed_utils/run_main.py
bioshed/src/bioshed_atlas/bioshed_utils/run_main_test.py
bioshed/src/bioshed_atlas/files/__init__.py
bioshed/src/bioshed_atlas/files/search_encode_assay.txt
bioshed/src/bioshed_atlas/files/search_encode_assaycategory.txt
bioshed/src/bioshed_atlas/files/search_encode_assaytarget.txt
bioshed/src/bioshed_atlas/files/search_encode_assaytype.txt
bioshed/src/bioshed_atlas/files/search_encode_celltype.txt
bioshed/src/bioshed_atlas/files/search_encode_disease.txt
bioshed/src/bioshed_atlas/files/search_encode_filetype.txt
bioshed/src/bioshed_atlas/files/search_encode_genome.txt
bioshed/src/bioshed_atlas/files/search_encode_platform.txt
bioshed/src/bioshed_atlas/files/search_encode_species.txt
bioshed/src/bioshed_atlas/files/search_encode_tissue.txt
bioshed/src/bioshed_utils/__init__.py
bioshed/src/bioshed_utils/aws_batch_utils.py
bioshed/src/bioshed_utils/aws_config_constants.json
bioshed/src/bioshed_utils/aws_s3_utils.py
bioshed/src/bioshed_utils/docker_utils.py
bioshed/src/bioshed_utils/file_utils.py
bioshed/src/bioshed_utils/lambda_utils.py
bioshed-0.2.10.dist-info/LICENSE.txt
bioshed-0.2.10.dist-info/METADATA
bioshed-0.2.10.dist-info/WHEEL
bioshed-0.2.10.dist-info/entry_points.txt
bioshed-0.2.10.dist-info/top_level.txt
bioshed-0.2.10.dist-info/RECORD
